code_duplicates_cli/__init__.py
code_duplicates_cli/cli.py
code_duplicates_cli/core/__init__.py
code_duplicates_cli/core/config.py
code_duplicates_cli/core/embeddings.py
code_duplicates_cli/core/report.py
code_duplicates_cli/core/similarity.py
code_duplicates_cli/core/utils.py
code_duplicates_cli/core/extractors/base_extractor.py
code_duplicates_cli/core/extractors/code_extractor.py
code_duplicates_cli/core/extractors/parser_manager.py
code_duplicates_cli/core/extractors/regex_extractor.py
code_duplicates_cli/core/extractors/simple_extractor.py
code_duplicates_cli-3.0.0.dist-info/licenses/LICENSE
code_duplicates_cli-3.0.0.dist-info/METADATA
code_duplicates_cli-3.0.0.dist-info/WHEEL
code_duplicates_cli-3.0.0.dist-info/entry_points.txt
code_duplicates_cli-3.0.0.dist-info/top_level.txt
code_duplicates_cli-3.0.0.dist-info/RECORD
