Metadata-Version: 2.4
Name: code-duplicates-cli
Version: 3.0.0
Summary: Multi-language code duplicate detector using semantic embeddings and Tree-Sitter parsing
Author-email: Dario Soria <dssupertech@gmail.com>
Maintainer-email: Dario Soria <dssupertech@gmail.com>
License: MIT
Project-URL: Homepage, https://github.com/RDSoria/code-duplicates-cli
Project-URL: Repository, https://github.com/RDSoria/code-duplicates-cli
Project-URL: Issues, https://github.com/RDSoria/code-duplicates-cli/issues
Project-URL: Documentation, https://github.com/RDSoria/code-duplicates-cli#readme
Keywords: code-analysis,duplicate-detection,semantic-embeddings,tree-sitter,cli
Classifier: Development Status :: 4 - Beta
Classifier: Intended Audience :: Developers
Classifier: License :: OSI Approved :: MIT License
Classifier: Operating System :: OS Independent
Classifier: Programming Language :: Python :: 3
Classifier: Programming Language :: Python :: 3.8
Classifier: Programming Language :: Python :: 3.9
Classifier: Programming Language :: Python :: 3.10
Classifier: Programming Language :: Python :: 3.11
Classifier: Programming Language :: Python :: 3.12
Classifier: Topic :: Software Development :: Quality Assurance
Classifier: Topic :: Software Development :: Libraries :: Python Modules
Classifier: Environment :: Console
Requires-Python: >=3.8
License-File: LICENSE
Requires-Dist: typer>=0.12.3
Requires-Dist: tqdm>=4.66.0
Requires-Dist: sentence-transformers>=2.7.0
Requires-Dist: faiss-cpu>=1.8.0
Requires-Dist: tree-sitter>=0.22.3
Requires-Dist: tree-sitter-python>=0.21.0
Requires-Dist: tree-sitter-javascript>=0.21.0
Requires-Dist: jinja2>=3.1.4
Requires-Dist: pygments>=2.18.0
Requires-Dist: orjson>=3.10.7
Requires-Dist: joblib>=1.4.2
Provides-Extra: dev
Requires-Dist: pytest>=7.0.0; extra == "dev"
Requires-Dist: pytest-cov>=4.0.0; extra == "dev"
Requires-Dist: black>=23.0.0; extra == "dev"
Requires-Dist: isort>=5.12.0; extra == "dev"
Requires-Dist: flake8>=6.0.0; extra == "dev"
Requires-Dist: mypy>=1.0.0; extra == "dev"
Dynamic: license-file
